{
  "name": "liquidity-migration",
  "license": "UNLICENSED",
  "scripts": {
    "codegen": "graph codegen",
    "build": "graph build",
    "deploy": "graph deploy --node https://api.thegraph.com/deploy/ --ipfs https://api.thegraph.com/ipfs/ ensofinance/enso-liquidity-migration",
    "create-local": "graph create --node http://localhost:8020/ ensofinance/enso-liquidity-migration",
    "remove-local": "graph remove --node http://localhost:8020/ ensofinance/enso-liquidity-migration",
    "deploy-local": "graph deploy --node http://localhost:8020/ --ipfs http://localhost:5001 ensofinance/enso-liquidity-migration"
  },
  "dependencies": {
    "@graphprotocol/graph-cli": "0.25.0",
    "@graphprotocol/graph-ts": "0.24.1"
  }
}
